setup.py
kvndb/__init__.py
kvndb/__main__.py
kvndb/cmdclient.py
kvndb/data.py
kvndb/dbmdb.py
kvndb/dbproto.py
kvndb/dirdb.py
kvndb/ramdb.py
kvndb/router.py
kvndb/runner.py
kvndb/txclient.py
kvndb/utils.py
kvndb.egg-info/PKG-INFO
kvndb.egg-info/SOURCES.txt
kvndb.egg-info/dependency_links.txt
kvndb.egg-info/entry_points.txt
kvndb.egg-info/not-zip-safe
kvndb.egg-info/requires.txt
kvndb.egg-info/top_level.txt