Metadata-Version: 1.1
Name: kvndb
Version: 0.1
Summary: A modular Key/Value Network Database server+client using twisted
Home-page: https://github.com/bennr01/kvndb/
Author: bennr01
Author-email: benjamin99.vogt@web.de
License: MIT
Keywords: database key value network scalable
Platform: UNKNOWN
Classifier: Development Status :: 3 - Alpha
Classifier: License :: OSI Approved :: MIT License
Classifier: Programming Language :: Python :: 2.7
Classifier: Topic :: Database
